srbpy/__init__.py
srbpy/extension.py
srbpy/alignment/__init__.py
srbpy/alignment/align.py
srbpy/alignment/align_base.py
srbpy/alignment/align_bx.py
srbpy/alignment/align_cg.py
srbpy/alignment/align_dmx.py
srbpy/alignment/align_pqx.cp312-win_amd64.pyd
srbpy/alignment/align_sqx.py
srbpy/model/__init__.py
srbpy/model/core.py
srbpy/public/__init__.py
srbpy/public/gfunc.cp312-win_amd64.pyd
srbpy/server/__init__.py
srbpy/server/json_encoders.py
srbpy/server/orm.py
srbpy/server/srb_server.py
srbpy/stdlib/__init__.py
srbpy/stdlib/auxiliary.py
srbpy/stdlib/base.py
srbpy/stdlib/foundations.py
srbpy/stdlib/substructures.py
srbpy/stdlib/supstructures.py
srbpy-0.2.3.dist-info/LICENSE
srbpy-0.2.3.dist-info/METADATA
srbpy-0.2.3.dist-info/WHEEL
srbpy-0.2.3.dist-info/top_level.txt
srbpy-0.2.3.dist-info/RECORD
