Metadata-Version: 2.1
Name: srbpy
Version: 0.2.3
Summary: A Python/C++ Mixed Road Bridge Design Package
Home-page: https://github.com/billhu0228/SmartRoadBridgePy
Author: Bill Hu
Author-email: billhu0228@icloud.com
License: MIT
Project-URL: Source, https://github.com/billhu0228/SmartRoadBridgePy
Keywords: civil road bridge alignment
Classifier: Development Status :: 3 - Alpha
Classifier: Intended Audience :: Developers
Classifier: Programming Language :: Python :: 3.7
Classifier: Programming Language :: Python :: 3.8
Classifier: Programming Language :: Python :: 3.9
Classifier: Programming Language :: Python :: 3.10
Classifier: Programming Language :: Python :: 3.12
Classifier: License :: OSI Approved :: MIT License
Classifier: Operating System :: OS Independent
Requires-Python: >=3
License-File: LICENSE
Requires-Dist: numpy
Requires-Dist: scikit-spatial >=4.0.0
Requires-Dist: PyAngle >=2.2.0
Requires-Dist: pybind11 >=2.6.0
Requires-Dist: SQLAlchemy >=1.3
Requires-Dist: ezdxf >=0.17
Requires-Dist: requests >=2.27
